{
  "updated": "2026-07-08T05:13:40Z",
  "data": {
    "us_QQQ": {
      "today": -1.85,
      "price": 709.43
    },
    "us_SPY": {
      "today": -0.48,
      "price": 747.71
    },
    "us_RING": {
      "today": -3.48,
      "price": 65.38
    },
    "us_COPX": {
      "today": -4.91,
      "price": 74.63
    },
    "us_BITB": {
      "today": 0.14,
      "price": 34.63
    },
    "hk_03455": {
      "today": -0.59,
      "price": 5582.0
    },
    "hk_03132": {
      "today": -0.67,
      "price": 65.46
    },
    "hk_03147": {
      "today": 1.21,
      "price": 15.9
    },
    "hk_03110": {
      "today": 1.09,
      "price": 29.6
    },
    "hk_02840": {
      "today": -0.07,
      "price": 2966.0
    },
    "cn_513390": {
      "today": -1.05,
      "price": 2.36
    },
    "cn_159652": {
      "today": -1.36,
      "price": 1.525
    },
    "cn_588200": {
      "today": 3.11,
      "price": 4.57
    },
    "cn_515880": {
      "today": 1.18,
      "price": 0.77
    },
    "cn_518880": {
      "today": -0.02,
      "price": 8.595
    },
    "watch_300782": {
      "today": 0.9,
      "price": 92.24
    },
    "watch_MRVL": {
      "today": -7.45,
      "price": 230.7
    },
    "watch_AAOI": {
      "today": -7.26,
      "price": 114.41
    }
  }
}