{
  "updated": "2026-05-20T00:04:04Z",
  "data": {
    "us_QQQ": {
      "today": -0.62,
      "price": 701.53
    },
    "us_SPY": {
      "today": -0.67,
      "price": 733.73
    },
    "us_RING": {
      "today": -3.85,
      "price": 72.98
    },
    "us_COPX": {
      "today": -3.03,
      "price": 79.37
    },
    "us_BITB": {
      "today": -0.12,
      "price": 41.68
    },
    "hk_03455": {
      "today": 0.05,
      "price": 5532.0
    },
    "hk_03132": {
      "today": -2.0,
      "price": 59.92
    },
    "hk_03147": {
      "today": -0.44,
      "price": 15.8
    },
    "hk_03110": {
      "today": 0.25,
      "price": 32.6
    },
    "hk_02840": {
      "today": 0.28,
      "price": 3275.0
    },
    "cn_513390": {
      "today": -0.4,
      "price": 2.261
    },
    "cn_159652": {
      "today": -1.27,
      "price": 1.714
    },
    "cn_588200": {
      "today": 3.93,
      "price": 3.594
    },
    "cn_515880": {
      "today": -0.4,
      "price": 1.511
    },
    "cn_518880": {
      "today": 0.02,
      "price": 9.515
    },
    "watch_300782": {
      "today": -1.08,
      "price": 129.39
    },
    "watch_MRVL": {
      "today": 4.34,
      "price": 176.27
    },
    "watch_AAOI": {
      "today": -1.11,
      "price": 171.33
    }
  }
}